Metadata-Version: 2.1
Name: example-pkg-aaronndx
Version: 0.0.2
Summary: This is a demo for python setup tools
Home-page: https://www.baidu.com
Author: Aaron Hu
Author-email: aaronndx@g.ucla.edu
License: UNKNOWN
Project-URL: Bug Tracker, https://github.com
Platform: UNKNOWN
Classifier: Programming Language :: Python :: 3
Classifier: License :: OSI Approved :: MIT License
Classifier: Operating System :: OS Independent
Requires-Python: >=3.6
License-File: LICENSE
